d-flipflop/d.vhdl
library ieee;
use ieee.std_logic_1164.all;

entity d is
    port(
        a,clk:in std_logic;
        z:out std_logic
    );
end d;

architecture behavior of d is
  begin
    process(a,clk)
     begin
        if(clk'event and clk='1') then
            z<=a;
        end if;
     end process;
    end behavior;

d-flipflop/d_tb.vhdl
library ieee;
use ieee.std_logic_1164.all;

entity d_tb is
end d_tb;

architecture behavior of d_tb is
    signal a_tb, clk_tb: std_logic := '0';  
    signal z_tb: std_logic;
begin
    mapp: entity work.d port map (a_tb, clk_tb, z_tb);

    clk_process: process
    begin
        while now < 80 ns loop
            clk_tb <= '0';  
            wait for 100 ps;
            clk_tb <= not clk_tb;
            wait for 100 ps;
        end loop;
        wait;
    end process;

    stimulus_process: process
    begin
        a_tb <= '0';  
        wait for 20 ns;
        a_tb <= '1';
        wait for 20 ns;
       
        a_tb <= '0';  
        wait for 20 ns;
        a_tb <= '1';
        wait for 20 ns;

        wait;
    end process;

end behavior;

d-flipflop/result.vcd
$date
  Sat Feb 10 20:13:11 2024
$end
$version
  GHDL v0
$end
$timescale
  1 fs
$end
$scope module standard $end
$upscope $end
$scope module std_logic_1164 $end
$upscope $end
$scope module d_tb $end
$var reg 1 ! a_tb $end
$var reg 1 " clk_tb $end
$var reg 1 # z_tb $end
$scope module mapp $end
$var reg 1 $ a $end
$var reg 1 % clk $end
$var reg 1 & z $end
$upscope $end
$upscope $end
$enddefinitions $end
#0
0!
0"
U#
0$
0%
U&
#100000
1"
0#
1%
0&
#200000
0"
0%
#300000
1"
1%
#400000
0"
0%
#500000
1"
1%
#600000
0"
0%
#700000
1"
1%
#800000
0"
0%
#900000
1"
1%
#1000000
0"
0%
#1100000
1"
1%
#1200000
0"
0%
#1300000
1"
1%
#1400000
0"
0%
#1500000
1"
1%
#1600000
0"
0%
#1700000
1"
1%
#1800000
0"
0%
#1900000
1"
1%
#2000000
0"
0%
#2100000
1"
1%
#2200000
0"
0%
#2300000
1"
1%
#2400000
0"
0%
#2500000
1"
1%
#2600000
0"
0%
#2700000
1"
1%
#2800000
0"
0%
#2900000
1"
1%
#3000000
0"
0%
#3100000
1"
1%
#3200000
0"
0%
#3300000
1"
1%
#3400000
0"
0%
#3500000
1"
1%
#3600000
0"
0%
#3700000
1"
1%
#3800000
0"
0%
#3900000
1"
1%
#4000000
0"
0%
#4100000
1"
1%
#4200000
0"
0%
#4300000
1"
1%
#4400000
0"
0%
#4500000
1"
1%
#4600000
0"
0%
#4700000
1"
1%
#4800000
0"
0%
#4900000
1"
1%
#5000000
0"
0%
#5100000
1"
1%
#5200000
0"
0%
#5300000
1"
1%
#5400000
0"
0%
#5500000
1"
1%
#5600000
0"
0%
#5700000
1"
1%
#5800000
0"
0%
#5900000
1"
1%
#6000000
0"
0%
#6100000
1"
1%
#6200000
0"
0%
#6300000
1"
1%
#6400000
0"
0%
#6500000
1"
1%
#6600000
0"
0%
#6700000
1"
1%
#6800000
0"
0%
#6900000
1"
1%
#7000000
0"
0%
#7100000
1"
1%
#7200000
0"
0%
#7300000
1"
1%
#7400000
0"
0%
#7500000
1"
1%
#7600000
0"
0%
#7700000
1"
1%
#7800000
0"
0%
#7900000
1"
1%
#8000000
0"
0%
#8100000
1"
1%
#8200000
0"
0%
#8300000
1"
1%
#8400000
0"
0%
#8500000
1"
1%
#8600000
0"
0%
#8700000
1"
1%
#8800000
0"
0%
#8900000
1"
1%
#9000000
0"
0%
#9100000
1"
1%
#9200000
0"
0%
#9300000
1"
1%
#9400000
0"
0%
#9500000
1"
1%
#9600000
0"
0%
#9700000
1"
1%
#9800000
0"
0%
#9900000
1"
1%
#10000000
0"
0%
#10100000
1"
1%
#10200000
0"
0%
#10300000
1"
1%
#10400000
0"
0%
#10500000
1"
1%
#10600000
0"
0%
#10700000
1"
1%
#10800000
0"
0%
#10900000
1"
1%
#11000000
0"
0%
#11100000
1"
1%
#11200000
0"
0%
#11300000
1"
1%
#11400000
0"
0%
#11500000
1"
1%
#11600000
0"
0%
#11700000
1"
1%
#11800000
0"
0%
#11900000
1"
1%
#12000000
0"
0%
#12100000
1"
1%
#12200000
0"
0%
#12300000
1"
1%
#12400000
0"
0%
#12500000
1"
1%
#12600000
0"
0%
#12700000
1"
1%
#12800000
0"
0%
#12900000
1"
1%
#13000000
0"
0%
#13100000
1"
1%
#13200000
0"
0%
#13300000
1"
1%
#13400000
0"
0%
#13500000
1"
1%
#13600000
0"
0%
#13700000
1"
1%
#13800000
0"
0%
#13900000
1"
1%
#14000000
0"
0%
#14100000
1"
1%
#14200000
0"
0%
#14300000
1"
1%
#14400000
0"
0%
#14500000
1"
1%
#14600000
0"
0%
#14700000
1"
1%
#14800000
0"
0%
#14900000
1"
1%
#15000000
0"
0%
#15100000
1"
1%
#15200000
0"
0%
#15300000
1"
1%
#15400000
0"
0%
#15500000
1"
1%
#15600000
0"
0%
#15700000
1"
1%
#15800000
0"
0%
#15900000
1"
1%
#16000000
0"
0%
#16100000
1"
1%
#16200000
0"
0%
#16300000
1"
1%
#16400000
0"
0%
#16500000
1"
1%
#16600000
0"
0%
#16700000
1"
1%
#16800000
0"
0%
#16900000
1"
1%
#17000000
0"
0%
#17100000
1"
1%
#17200000
0"
0%
#17300000
1"
1%
#17400000
0"
0%
#17500000
1"
1%
#17600000
0"
0%
#17700000
1"
1%
#17800000
0"
0%
#17900000
1"
1%
#18000000
0"
0%
#18100000
1"
1%
#18200000
0"
0%
#18300000
1"
1%
#18400000
0"
0%
#18500000
1"
1%
#18600000
0"
0%
#18700000
1"
1%
#18800000
0"
0%
#18900000
1"
1%
#19000000
0"
0%
#19100000
1"
1%
#19200000
0"
0%
#19300000
1"
1%
#19400000
0"
0%
#19500000
1"
1%
#19600000
0"
0%
#19700000
1"
1%
#19800000
0"
0%
#19900000
1"
1%
#20000000
1!
0"
1$
0%
#20100000
1"
1#
1%
1&
#20200000
0"
0%
#20300000
1"
1%
#20400000
0"
0%
#20500000
1"
1%
#20600000
0"
0%
#20700000
1"
1%
#20800000
0"
0%
#20900000
1"
1%
#21000000
0"
0%
#21100000
1"
1%
#21200000
0"
0%
#21300000
1"
1%
#21400000
0"
0%
#21500000
1"
1%
#21600000
0"
0%
#21700000
1"
1%
#21800000
0"
0%
#21900000
1"
1%
#22000000
0"
0%
#22100000
1"
1%
#22200000
0"
0%
#22300000
1"
1%
#22400000
0"
0%
#22500000
1"
1%
#22600000
0"
0%
#22700000
1"
1%
#22800000
0"
0%
#22900000
1"
1%
#23000000
0"
0%
#23100000
1"
1%
#23200000
0"
0%
#23300000
1"
1%
#23400000
0"
0%
#23500000
1"
1%
#23600000
0"
0%
#23700000
1"
1%
#23800000
0"
0%
#23900000
1"
1%
#24000000
0"
0%
#24100000
1"
1%
#24200000
0"
0%
#24300000
1"
1%
#24400000
0"
0%
#24500000
1"
1%
#24600000
0"
0%
#24700000
1"
1%
#24800000
0"
0%
#24900000
1"
1%
#25000000
0"
0%
#25100000
1"
1%
#25200000
0"
0%
#25300000
1"
1%
#25400000
0"
0%
#25500000
1"
1%
#25600000
0"
0%
#25700000
1"
1%
#25800000
0"
0%
#25900000
1"
1%
#26000000
0"
0%
#26100000
1"
1%
#26200000
0"
0%
#26300000
1"
1%
#26400000
0"
0%
#26500000
1"
1%
#26600000
0"
0%
#26700000
1"
1%
#26800000
0"
0%
#26900000
1"
1%
#27000000
0"
0%
#27100000
1"
1%
#27200000
0"
0%
#27300000
1"
1%
#27400000
0"
0%
#27500000
1"
1%
#27600000
0"
0%
#27700000
1"
1%
#27800000
0"
0%
#27900000
1"
1%
#28000000
0"
0%
#28100000
1"
1%
#28200000
0"
0%
#28300000
1"
1%
#28400000
0"
0%
#28500000
1"
1%
#28600000
0"
0%
#28700000
1"
1%
#28800000
0"
0%
#28900000
1"
1%
#29000000
0"
0%
#29100000
1"
1%
#29200000
0"
0%
#29300000
1"
1%
#29400000
0"
0%
#29500000
1"
1%
#29600000
0"
0%
#29700000
1"
1%
#29800000
0"
0%
#29900000
1"
1%
#30000000
0"
0%
#30100000
1"
1%
#30200000
0"
0%
#30300000
1"
1%
#30400000
0"
0%
#30500000
1"
1%
#30600000
0"
0%
#30700000
1"
1%
#30800000
0"
0%
#30900000
1"
1%
#31000000
0"
0%
#31100000
1"
1%
#31200000
0"
0%
#31300000
1"
1%
#31400000
0"
0%
#31500000
1"
1%
#31600000
0"
0%
#31700000
1"
1%
#31800000
0"
0%
#31900000
1"
1%
#32000000
0"
0%
#32100000
1"
1%
#32200000
0"
0%
#32300000
1"
1%
#32400000
0"
0%
#32500000
1"
1%
#32600000
0"
0%
#32700000
1"
1%
#32800000
0"
0%
#32900000
1"
1%
#33000000
0"
0%
#33100000
1"
1%
#33200000
0"
0%
#33300000
1"
1%
#33400000
0"
0%
#33500000
1"
1%
#33600000
0"
0%
#33700000
1"
1%
#33800000
0"
0%
#33900000
1"
1%
#34000000
0"
0%
#34100000
1"
1%
#34200000
0"
0%
#34300000
1"
1%
#34400000
0"
0%
#34500000
1"
1%
#34600000
0"
0%
#34700000
1"
1%
#34800000
0"
0%
#34900000
1"
1%
#35000000
0"
0%
#35100000
1"
1%
#35200000
0"
0%
#35300000
1"
1%
#35400000
0"
0%
#35500000
1"
1%
#35600000
0"
0%
#35700000
1"
1%
#35800000
0"
0%
#35900000
1"
1%
#36000000
0"
0%
#36100000
1"
1%
#36200000
0"
0%
#36300000
1"
1%
#36400000
0"
0%
#36500000
1"
1%
#36600000
0"
0%
#36700000
1"
1%
#36800000
0"
0%
#36900000
1"
1%
#37000000
0"
0%
#37100000
1"
1%
#37200000
0"
0%
#37300000
1"
1%
#37400000
0"
0%
#37500000
1"
1%
#37600000
0"
0%
#37700000
1"
1%
#37800000
0"
0%
#37900000
1"
1%
#38000000
0"
0%
#38100000
1"
1%
#38200000
0"
0%
#38300000
1"
1%
#38400000
0"
0%
#38500000
1"
1%
#38600000
0"
0%
#38700000
1"
1%
#38800000
0"
0%
#38900000
1"
1%
#39000000
0"
0%
#39100000
1"
1%
#39200000
0"
0%
#39300000
1"
1%
#39400000
0"
0%
#39500000
1"
1%
#39600000
0"
0%
#39700000
1"
1%
#39800000
0"
0%
#39900000
1"
1%
#40000000
0!
0"
0$
0%
#40100000
1"
0#
1%
0&
#40200000
0"
0%
#40300000
1"
1%
#40400000
0"
0%
#40500000
1"
1%
#40600000
0"
0%
#40700000
1"
1%
#40800000
0"
0%
#40900000
1"
1%
#41000000
0"
0%
#41100000
1"
1%
#41200000
0"
0%
#41300000
1"
1%
#41400000
0"
0%
#41500000
1"
1%
#41600000
0"
0%
#41700000
1"
1%
#41800000
0"
0%
#41900000
1"
1%
#42000000
0"
0%
#42100000
1"
1%
#42200000
0"
0%
#42300000
1"
1%
#42400000
0"
0%
#42500000
1"
1%
#42600000
0"
0%
#42700000
1"
1%
#42800000
0"
0%
#42900000
1"
1%
#43000000
0"
0%
#43100000
1"
1%
#43200000
0"
0%
#43300000
1"
1%
#43400000
0"
0%
#43500000
1"
1%
#43600000
0"
0%
#43700000
1"
1%
#43800000
0"
0%
#43900000
1"
1%
#44000000
0"
0%
#44100000
1"
1%
#44200000
0"
0%
#44300000
1"
1%
#44400000
0"
0%
#44500000
1"
1%
#44600000
0"
0%
#44700000
1"
1%
#44800000
0"
0%
#44900000
1"
1%
#45000000
0"
0%
#45100000
1"
1%
#45200000
0"
0%
#45300000
1"
1%
#45400000
0"
0%
#45500000
1"
1%
#45600000
0"
0%
#45700000
1"
1%
#45800000
0"
0%
#45900000
1"
1%
#46000000
0"
0%
#46100000
1"
1%
#46200000
0"
0%
#46300000
1"
1%
#46400000
0"
0%
#46500000
1"
1%
#46600000
0"
0%
#46700000
1"
1%
#46800000
0"
0%
#46900000
1"
1%
#47000000
0"
0%
#47100000
1"
1%
#47200000
0"
0%
#47300000
1"
1%
#47400000
0"
0%
#47500000
1"
1%
#47600000
0"
0%
#47700000
1"
1%
#47800000
0"
0%
#47900000
1"
1%
#48000000
0"
0%
#48100000
1"
1%
#48200000
0"
0%
#48300000
1"
1%
#48400000
0"
0%
#48500000
1"
1%
#48600000
0"
0%
#48700000
1"
1%
#48800000
0"
0%
#48900000
1"
1%
#49000000
0"
0%
#49100000
1"
1%
#49200000
0"
0%
#49300000
1"
1%
#49400000
0"
0%
#49500000
1"
1%
#49600000
0"
0%
#49700000
1"
1%
#49800000
0"
0%
#49900000
1"
1%
#50000000
0"
0%
#50100000
1"
1%
#50200000
0"
0%
#50300000
1"
1%
#50400000
0"
0%
#50500000
1"
1%
#50600000
0"
0%
#50700000
1"
1%
#50800000
0"
0%
#50900000
1"
1%
#51000000
0"
0%
#51100000
1"
1%
#51200000
0"
0%
#51300000
1"
1%
#51400000
0"
0%
#51500000
1"
1%
#51600000
0"
0%
#51700000
1"
1%
#51800000
0"
0%
#51900000
1"
1%
#52000000
0"
0%
#52100000
1"
1%
#52200000
0"
0%
#52300000
1"
1%
#52400000
0"
0%
#52500000
1"
1%
#52600000
0"
0%
#52700000
1"
1%
#52800000
0"
0%
#52900000
1"
1%
#53000000
0"
0%
#53100000
1"
1%
#53200000
0"
0%
#53300000
1"
1%
#53400000
0"
0%
#53500000
1"
1%
#53600000
0"
0%
#53700000
1"
1%
#53800000
0"
0%
#53900000
1"
1%
#54000000
0"
0%
#54100000
1"
1%
#54200000
0"
0%
#54300000
1"
1%
#54400000
0"
0%
#54500000
1"
1%
#54600000
0"
0%
#54700000
1"
1%
#54800000
0"
0%
#54900000
1"
1%
#55000000
0"
0%
#55100000
1"
1%
#55200000
0"
0%
#55300000
1"
1%
#55400000
0"
0%
#55500000
1"
1%
#55600000
0"
0%
#55700000
1"
1%
#55800000
0"
0%
#55900000
1"
1%
#56000000
0"
0%
#56100000
1"
1%
#56200000
0"
0%
#56300000
1"
1%
#56400000
0"
0%
#56500000
1"
1%
#56600000
0"
0%
#56700000
1"
1%
#56800000
0"
0%
#56900000
1"
1%
#57000000
0"
0%
#57100000
1"
1%
#57200000
0"
0%
#57300000
1"
1%
#57400000
0"
0%
#57500000
1"
1%
#57600000
0"
0%
#57700000
1"
1%
#57800000
0"
0%
#57900000
1"
1%
#58000000
0"
0%
#58100000
1"
1%
#58200000
0"
0%
#58300000
1"
1%
#58400000
0"
0%
#58500000
1"
1%
#58600000
0"
0%
#58700000
1"
1%
#58800000
0"
0%
#58900000
1"
1%
#59000000
0"
0%
#59100000
1"
1%
#59200000
0"
0%
#59300000
1"
1%
#59400000
0"
0%
#59500000
1"
1%
#59600000
0"
0%
#59700000
1"
1%
#59800000
0"
0%
#59900000
1"
1%
#60000000
1!
0"
1$
0%
#60100000
1"
1#
1%
1&
