jk-flipflop/jk.vhdl
library ieee;
use ieee.std_logic_1164.all;

entity jk is
port(
    j, k, clk: in std_logic;
    q, qN: out std_logic
);
end jk;

architecture behavior of jk is
   signal temp: std_logic;

begin
    process(clk, j, k)
    begin
        if (rising_edge(clk)) then
            if (j = '0' and k = '0') then
                temp <= temp;
            elsif (j = '0' and k = '1') then
                temp <= '0';
            elsif (j = '1' and k = '0') then
                temp <= '1';
            elsif (j = '1' and k = '1') then
                temp <= not temp;
            end if;
        end if;
        q <= temp;
        qN <= not temp;
    end process;
    
 
end behavior;

jk-flipflop/jk_tb.vhdl
library ieee;
use ieee.std_logic_1164.all;

entity jk_tb is
end jk_tb;

architecture behavior of jk_tb is

    --constant CLK_PERIOD: time := 10 ns; -- Clock period

    signal j_tb, k_tb: std_logic;
    signal clk_tb: std_logic;
    signal q_tb, qN_tb: std_logic;


begin

    dut:entity work.jk port map (j_tb,k_tb,clk_tb,q_tb,qN_tb);

    clk_process: process
    begin
        while now < 80 ns loop
            clk_tb <= '0';
            wait for 5 ns;
            clk_tb <= not clk_tb;
            wait for 5 ns;
        end loop;
        wait;
    end process;

    stimulus_process: process
    begin
        j_tb <= '0';
        k_tb <= '0';
        wait for 20 ns;

        j_tb <= '0';
        k_tb <= '1';
        wait for 20 ns;

        j_tb <= '1';
        k_tb <= '0';
        wait for 20 ns;

        j_tb <= '1';
        k_tb <= '1';
        wait for 20 ns;

        wait;
    end process;

end behavior;

jk-flipflop/result.vcd
$date
  Sat Feb 10 12:53:46 2024
$end
$version
  GHDL v0
$end
$timescale
  1 fs
$end
$scope module standard $end
$upscope $end
$scope module std_logic_1164 $end
$upscope $end
$scope module jk_tb $end
$var reg 1 ! j_tb $end
$var reg 1 " k_tb $end
$var reg 1 # clk_tb $end
$var reg 1 $ q_tb $end
$var reg 1 % qn_tb $end
$scope module dut $end
$var reg 1 & j $end
$var reg 1 ' k $end
$var reg 1 ( clk $end
$var reg 1 ) q $end
$var reg 1 * qn $end
$var reg 1 + temp $end
$upscope $end
$upscope $end
$enddefinitions $end
#0
0!
0"
0#
U$
U%
0&
0'
0(
U)
U*
U+
#5000000
1#
1(
#10000000
0#
0(
#15000000
1#
1(
#20000000
1"
0#
1'
0(
#25000000
1#
1(
0+
#30000000
0#
0$
1%
0(
0)
1*
#35000000
1#
1(
#40000000
1!
0"
0#
1&
0'
0(
#45000000
1#
1(
1+
#50000000
0#
1$
0%
0(
1)
0*
#55000000
1#
1(
#60000000
1"
0#
1'
0(
#65000000
1#
1(
0+
#70000000
0#
0$
1%
0(
0)
1*
#75000000
1#
1(
1+
#80000000
0#
1$
0%
0(
1)
0*
#85000000
1#
1(
0+
#90000000
0#
0$
1%
0(
0)
1*
#95000000
1#
1(
1+
